LICENSE
README.md
pyproject.toml
setup.py
covalent_hpc_plugin/__init__.py
covalent_hpc_plugin/hpc.py
covalent_hpc_plugin.egg-info/PKG-INFO
covalent_hpc_plugin.egg-info/SOURCES.txt
covalent_hpc_plugin.egg-info/dependency_links.txt
covalent_hpc_plugin.egg-info/entry_points.txt
covalent_hpc_plugin.egg-info/requires.txt
covalent_hpc_plugin.egg-info/top_level.txt
tests/__init__.py
tests/test_hpc.py