Metadata-Version: 2.1
Name: covalent-hpc-plugin
Version: 0.0.1
Summary: Covalent HPC Plugin
Home-page: https://github.com/arosen93/covalent-hpc-plugin
Download-URL: https://github.com/arosen93/covalent-hpc-plugin/covalent-hpc-plugin/archive/v0.0.1.tar.gz
Author: Andrew S. Rosen
Maintainer: Andrew S. Rosen
License: GNU Affero GPL v3.0
Classifier: Development Status :: 4 - Beta
Classifier: Environment :: Console
Classifier: Environment :: Plugins
Classifier: Intended Audience :: Developers
Classifier: Intended Audience :: Education
Classifier: Intended Audience :: Science/Research
Classifier: License :: Other/Proprietary License
Classifier: Natural Language :: English
Classifier: Operating System :: MacOS
Classifier: Operating System :: POSIX :: Linux
Classifier: Programming Language :: Python :: 3
Classifier: Programming Language :: Python :: 3 :: Only
Classifier: Programming Language :: Python :: 3.8
Classifier: Programming Language :: Python :: 3.9
Classifier: Programming Language :: Python :: 3.10
Classifier: Topic :: Adaptive Technologies
Classifier: Topic :: Scientific/Engineering
Classifier: Topic :: Scientific/Engineering :: Interface Engine/Protocol Translator
Classifier: Topic :: Software Development
Classifier: Topic :: System :: Distributed Computing
License-File: LICENSE
